README.rst
setup.py
photostation/__init__.py
photostation/error.py
photostation/service.py
photostation/session.py
photostation/utils.py
photostation.egg-info/PKG-INFO
photostation.egg-info/SOURCES.txt
photostation.egg-info/dependency_links.txt
photostation.egg-info/requires.txt
photostation.egg-info/top_level.txt