Metadata-Version: 1.1
Name: photostation
Version: 0.1.5
Summary: A Python API to communicate with Photo Station running on Synology NAS.
Home-page: https://github.com/skarppi/python-photostation
Author: Juho Kolehmainen
Author-email: juho.kolehmainen@iki.fi
License: MIT
Keywords: synology dsm photo station web api
Platform: UNKNOWN
Classifier: Development Status :: 3 - Alpha
Classifier: Intended Audience :: Developers
Classifier: License :: OSI Approved :: MIT License
Classifier: Programming Language :: Python :: 2
Classifier: Programming Language :: Python :: 2.7
Classifier: Programming Language :: Python :: 3
Classifier: Programming Language :: Python :: 3.6
Classifier: Topic :: Software Development :: Libraries :: Python Modules
